query_state_lib/__init__.py
query_state_lib/base/__init__.py
query_state_lib/base/executors/__init__.py
query_state_lib/base/executors/batch_work_executor.py
query_state_lib/base/executors/bounded_executor.py
query_state_lib/base/executors/fail_safe_executor.py
query_state_lib/base/executors/utils/__init__.py
query_state_lib/base/executors/utils/atomic_counter.py
query_state_lib/base/executors/utils/progress_logger.py
query_state_lib/base/executors/utils/retriable_value_error.py
query_state_lib/base/executors/utils/utils.py
query_state_lib/base/jobs/__init__.py
query_state_lib/base/jobs/base_job.py
query_state_lib/base/jobs/job_run_multithread.py
query_state_lib/base/jobs/utils/__init__.py
query_state_lib/base/jobs/utils/job_utils.py
query_state_lib/base/mappers/__init__.py
query_state_lib/base/mappers/eth_call_balance_of_mapper.py
query_state_lib/base/mappers/eth_call_mapper.py
query_state_lib/base/mappers/eth_json_rpc_mapper.py
query_state_lib/base/mappers/get_balance_mapper.py
query_state_lib/base/providers/__init__.py
query_state_lib/base/providers/auto.py
query_state_lib/base/providers/ipc.py
query_state_lib/base/providers/rpc.py
query_state_lib/base/utils/__init__.py
query_state_lib/base/utils/decoder.py
query_state_lib/base/utils/encoder.py
query_state_lib/client/__init__.py
query_state_lib/client/client_querier.py
query_state_lib/client/moralis_client/__init__.py
query_state_lib/client/moralis_client/client.py
query_state_lib/client/moralis_client/connection.py
query_state_lib/client/moralis_client/examples.py
query_state_lib/client/moralis_client/exceptions.py
query_state_lib/client/moralis_client/moralis_http.py
query_state_lib/client/moralis_client/moralis_request.py
query_state_lib/client/moralis_client/moralis_response.py
query_state_lib/client/moralis_client/resolver.py
query_state_lib/client/moralis_client/typings.py
query_state_lib/jobs/__init__.py
query_state_lib/jobs/handler_batch_request_job.py
query_state_lib/jobs/sent_batch_request_job.py
query_blockchain_state_lib-1.0.1.dist-info/LICENSE
query_blockchain_state_lib-1.0.1.dist-info/METADATA
query_blockchain_state_lib-1.0.1.dist-info/WHEEL
query_blockchain_state_lib-1.0.1.dist-info/top_level.txt
query_blockchain_state_lib-1.0.1.dist-info/RECORD
