Metadata-Version: 2.1
Name: query-blockchain-state-lib
Version: 1.0.1
Summary: Query EVM state data by batch
Home-page: https://github.com/Centic-io/query-blockchain-state-lib
Author: Viet-Bang Pham
Author-email: phamvietbang2965@gmail.com
Project-URL: Bug Tracker, https://github.com/Centic-io/query-blockchain-state-lib
Classifier: Programming Language :: Python :: 3
Classifier: License :: OSI Approved :: MIT License
Classifier: Operating System :: OS Independent
Requires-Python: >=3.6
License-File: LICENSE
Requires-Dist: web3 >=6.0.0
Requires-Dist: requests <=3.0.0
Requires-Dist: pbkdf2 <=1.3
